{
  "abstract" : "Returns information about your app’s authorization to access the user’s photo library.",
  "codeExamples" : [

  ],
  "contentHash" : "77537b7386e232335ee0025b82971ae39848a93a71f39f4dbaeba2028f5b8390",
  "crawledAt" : "2025-12-01T09:40:49Z",
  "declaration" : {
    "code" : "class func authorizationStatus() -> PHAuthorizationStatus",
    "language" : "swift"
  },
  "id" : "7635CC02-23FA-4912-8BBA-8C7E5F4A2EF4",
  "kind" : "method",
  "module" : "Photos",
  "overview" : "## Return Value\n\nThe current authorization status.",
  "platforms" : [
    "iOS",
    "iPadOS",
    "Mac Catalyst",
    "macOS",
    "tvOS",
    "visionOS"
  ],
  "rawMarkdown" : "---\nsource: https:\/\/developer.apple.com\/documentation\/Photos\/PHPhotoLibrary\/authorizationStatus()\ncrawled: 2025-12-01T09:40:49Z\n---\n\n# authorizationStatus()\n\n**Type Method**\n\nReturns information about your app’s authorization to access the user’s photo library.\n\n## Declaration\n\n```swift\nclass func authorizationStatus() -> PHAuthorizationStatus\n```\n\n## Return Value\n\nThe current authorization status.\n\n## Verifying Authorization\n\n- **authorizationStatus(for:)**: Returns the app’s authorization to access the user’s photo library for the specified access level.\n- **requestAuthorization(for:handler:)**: Prompts the user to grant the app permission to access the photo library.\n- **PHAccessLevel**: The app’s level of access to the user’s photo library.\n- **PHAuthorizationStatus**: Information about your app’s authorization to access the user’s photo library.\n- **requestAuthorization(_:)**: Requests the user’s permission, if needed, to access the photo library.\n\n",
  "sections" : [
    {
      "content" : "",
      "items" : [
        {
          "description" : "Returns the app’s authorization to access the user’s photo library for the specified access level.",
          "name" : "authorizationStatus(for:)",
          "url" : "https:\/\/developer.apple.com\/documentation\/Photos\/PHPhotoLibrary\/authorizationStatus(for:)"
        },
        {
          "description" : "Prompts the user to grant the app permission to access the photo library.",
          "name" : "requestAuthorization(for:handler:)",
          "url" : "https:\/\/developer.apple.com\/documentation\/Photos\/PHPhotoLibrary\/requestAuthorization(for:handler:)"
        },
        {
          "description" : "The app’s level of access to the user’s photo library.",
          "name" : "PHAccessLevel",
          "url" : "https:\/\/developer.apple.com\/documentation\/Photos\/PHAccessLevel"
        },
        {
          "description" : "Information about your app’s authorization to access the user’s photo library.",
          "name" : "PHAuthorizationStatus",
          "url" : "https:\/\/developer.apple.com\/documentation\/Photos\/PHAuthorizationStatus"
        },
        {
          "description" : "Requests the user’s permission, if needed, to access the photo library.",
          "name" : "requestAuthorization(_:)",
          "url" : "https:\/\/developer.apple.com\/documentation\/Photos\/PHPhotoLibrary\/requestAuthorization(_:)"
        }
      ],
      "title" : "Verifying Authorization"
    }
  ],
  "source" : "appleJSON",
  "title" : "authorizationStatus()",
  "url" : "https:\/\/developer.apple.com\/documentation\/Photos\/PHPhotoLibrary\/authorizationStatus()"
}