{
  "abstract" : "The reduction mode.",
  "codeExamples" : [

  ],
  "conformsTo" : [
    "BitwiseCopyable",
    "Equatable",
    "Hashable",
    "RawRepresentable",
    "Sendable",
    "SendableMetatype"
  ],
  "contentHash" : "b08594363d2fe6097212ad15a84b8b207852231fc63d5523dd9e17391681f424",
  "crawledAt" : "2026-03-10T20:17:54Z",
  "declaration" : {
    "code" : "enum MPSGraphReductionMode",
    "language" : "swift"
  },
  "id" : "31F16C11-C942-47FC-8190-E46881E2D9B9",
  "kind" : "enum",
  "language" : "swift",
  "module" : "Metal Performance Shaders Graph",
  "platforms" : [
    "iOS",
    "iPadOS",
    "Mac Catalyst",
    "macOS",
    "tvOS",
    "visionOS"
  ],
  "rawMarkdown" : "---\nsource: https:\/\/developer.apple.com\/documentation\/metalperformanceshadersgraph\/mpsgraphreductionmode\ncrawled: 2026-03-10T20:17:54Z\n---\n\n# MPSGraphReductionMode\n\n**Enumeration**\n\nThe reduction mode.\n\n## Declaration\n\n```swift\nenum MPSGraphReductionMode\n```\n\n## Enumeration Cases\n\n- **MPSGraphReductionMode.argumentMax**: Argument Max\n- **MPSGraphReductionMode.argumentMin**: Argument Min\n- **MPSGraphReductionMode.max**: Max\n- **MPSGraphReductionMode.min**: Min\n- **MPSGraphReductionMode.product**: Product\n- **MPSGraphReductionMode.sum**: Sum\n\n## Initializers\n\n- **init(rawValue:)**\n\n## Conforms To\n\n- BitwiseCopyable\n- Equatable\n- Hashable\n- RawRepresentable\n- Sendable\n- SendableMetatype\n\n",
  "sections" : [
    {
      "content" : "",
      "items" : [
        {
          "description" : "Argument Max",
          "name" : "MPSGraphReductionMode.argumentMax",
          "url" : "https:\/\/developer.apple.com\/documentation\/MetalPerformanceShadersGraph\/MPSGraphReductionMode\/argumentMax"
        },
        {
          "description" : "Argument Min",
          "name" : "MPSGraphReductionMode.argumentMin",
          "url" : "https:\/\/developer.apple.com\/documentation\/MetalPerformanceShadersGraph\/MPSGraphReductionMode\/argumentMin"
        },
        {
          "description" : "Max",
          "name" : "MPSGraphReductionMode.max",
          "url" : "https:\/\/developer.apple.com\/documentation\/MetalPerformanceShadersGraph\/MPSGraphReductionMode\/max"
        },
        {
          "description" : "Min",
          "name" : "MPSGraphReductionMode.min",
          "url" : "https:\/\/developer.apple.com\/documentation\/MetalPerformanceShadersGraph\/MPSGraphReductionMode\/min"
        },
        {
          "description" : "Product",
          "name" : "MPSGraphReductionMode.product",
          "url" : "https:\/\/developer.apple.com\/documentation\/MetalPerformanceShadersGraph\/MPSGraphReductionMode\/product"
        },
        {
          "description" : "Sum",
          "name" : "MPSGraphReductionMode.sum",
          "url" : "https:\/\/developer.apple.com\/documentation\/MetalPerformanceShadersGraph\/MPSGraphReductionMode\/sum"
        }
      ],
      "title" : "Enumeration Cases"
    },
    {
      "content" : "",
      "items" : [
        {
          "description" : "",
          "name" : "init(rawValue:)",
          "url" : "https:\/\/developer.apple.com\/documentation\/MetalPerformanceShadersGraph\/MPSGraphReductionMode\/init(rawValue:)"
        }
      ],
      "title" : "Initializers"
    }
  ],
  "source" : "appleJSON",
  "title" : "MPSGraphReductionMode",
  "url" : "https:\/\/developer.apple.com\/documentation\/metalperformanceshadersgraph\/mpsgraphreductionmode"
}