{
  "abstract" : "Direct the movements and animation of models.",
  "codeExamples" : [

  ],
  "contentHash" : "7b2f3127554d498a1d9f52a8c96c5def6e9145ad7880eafd2bb5e67822e20099",
  "crawledAt" : "2025-12-02T17:52:32Z",
  "id" : "D7979E4A-720F-429D-A52B-8E446B9B947B",
  "kind" : "collection",
  "language" : "swift",
  "module" : "RealityKit",
  "overview" : "## Overview\n\nGames and immersive game-like experiences often rely on animated character models to represent the player or non-player characters. The `CharacterControllerComponent` simplifies the process of moving a character around a scene. It handles basic movement, including navigating up and down stairs and slopes and jumping. It also allows you to sync the character movement with specific animations.\n\nTo further animate models in the scene, you may need to define a [doc:\/\/com.apple.RealityKit\/documentation\/RealityKit\/SkeletalPose] or adopt a full inverse kinematics solution with [doc:\/\/com.apple.RealityKit\/documentation\/RealityKit\/IKComponent].",
  "rawMarkdown" : "---\nsource: https:\/\/developer.apple.com\/documentation\/RealityKit\/game-development-character-skeletons\ncrawled: 2025-12-02T17:52:32Z\n---\n\n# Character control, skeletons, and inverse kinematics\n\n**API Collection**\n\nDirect the movements and animation of models.\n\n## Overview\n\nGames and immersive game-like experiences often rely on animated character models to represent the player or non-player characters. The `CharacterControllerComponent` simplifies the process of moving a character around a scene. It handles basic movement, including navigating up and down stairs and slopes and jumping. It also allows you to sync the character movement with specific animations.\n\nTo further animate models in the scene, you may need to define a [doc:\/\/com.apple.RealityKit\/documentation\/RealityKit\/SkeletalPose] or adopt a full inverse kinematics solution with [doc:\/\/com.apple.RealityKit\/documentation\/RealityKit\/IKComponent].\n\n## Character control\n\n- **CharacterControllerComponent**: A component that manages character movement.\n- **CharacterControllerComponent.Collision**: A container that holds collision state for the character controller.\n- **CharacterControllerComponent.CollisionFlags**: An option set that specifies which parts of the character capsule have collided with other objects.\n- **CharacterControllerStateComponent**: A component that represents the state of a character controller.\n\n## Skeletons\n\n- **SkeletalPosesComponent**: A component that exposes the collection of named animation skeletal poses.\n- **SkeletalPose**: A container that holds the position and orientation of each joint in a single animation skeleton.\n- **SkeletalPoseSet**: A collection of named skeletal poses.\n\n## Inverse kinematics components\n\n- **IKComponent**: A component that allows you to procedurally animate a skeletal model using a full body inverse kinematics solver.\n- **IKComponent.Joint**: The update stage object that lets you read and update the current settings of a single joint in an IK solver.\n- **IKComponent.JointCollection**: Ordered dictionary like container with fixed size.\n- **IKComponent.Solver**: The update stage object that lets you read and update the current settings of a single solver instance.\n- **IKComponent.SolverCollection**: Ordered dictionary like container with fixed size.\n- **IKComponent.Constraint**: The update stage object that lets you read and update the current settings of a single constraint in an IK solver.\n- **IKComponent.ConstraintCollection**: Ordered dictionary like container with fixed size.\n- **IKResource**: A reference counted immutable resource which contains one or more inverse kinematics solver rigs.\n- **IKSolverDefinition**: A container describing a solver instance.\n\n## Inverse kinematics rigs\n\n- **IKRig**: A full body inverse kinematics rig definition for a single skeleton.\n- **IKRig.Joint**: A definition of a rig joint and its IK solver settings.\n- **IKRig.JointCollection**: Ordered dictionary-like container with a fixed size.\n- **IKRig.Constraint**: A definition of a rig constraint.\n- **IKRig.ConstraintsCollection**: Ordered dictionary-like container.\n\n## Game development\n\n- **Gaming sample code projects**: Explore a collection of projects relating to game development.\n- **Entity animations**: Dynamically move, rotate, and scale entities at runtime.\n\n",
  "sections" : [
    {
      "content" : "",
      "items" : [
        {
          "description" : "A component that manages character movement.",
          "name" : "CharacterControllerComponent",
          "url" : "https:\/\/developer.apple.com\/documentation\/RealityKit\/CharacterControllerComponent"
        },
        {
          "description" : "A container that holds collision state for the character controller.",
          "name" : "CharacterControllerComponent.Collision",
          "url" : "https:\/\/developer.apple.com\/documentation\/RealityKit\/CharacterControllerComponent\/Collision"
        },
        {
          "description" : "An option set that specifies which parts of the character capsule have collided with other objects.",
          "name" : "CharacterControllerComponent.CollisionFlags",
          "url" : "https:\/\/developer.apple.com\/documentation\/RealityKit\/CharacterControllerComponent\/CollisionFlags"
        },
        {
          "description" : "A component that represents the state of a character controller.",
          "name" : "CharacterControllerStateComponent",
          "url" : "https:\/\/developer.apple.com\/documentation\/RealityKit\/CharacterControllerStateComponent"
        }
      ],
      "title" : "Character control"
    },
    {
      "content" : "",
      "items" : [
        {
          "description" : "A component that exposes the collection of named animation skeletal poses.",
          "name" : "SkeletalPosesComponent",
          "url" : "https:\/\/developer.apple.com\/documentation\/RealityKit\/SkeletalPosesComponent"
        },
        {
          "description" : "A container that holds the position and orientation of each joint in a single animation skeleton.",
          "name" : "SkeletalPose",
          "url" : "https:\/\/developer.apple.com\/documentation\/RealityKit\/SkeletalPose"
        },
        {
          "description" : "A collection of named skeletal poses.",
          "name" : "SkeletalPoseSet",
          "url" : "https:\/\/developer.apple.com\/documentation\/RealityKit\/SkeletalPoseSet"
        }
      ],
      "title" : "Skeletons"
    },
    {
      "content" : "",
      "items" : [
        {
          "description" : "A component that allows you to procedurally animate a skeletal model using a full body inverse kinematics solver.",
          "name" : "IKComponent",
          "url" : "https:\/\/developer.apple.com\/documentation\/RealityKit\/IKComponent"
        },
        {
          "description" : "The update stage object that lets you read and update the current settings of a single joint in an IK solver.",
          "name" : "IKComponent.Joint",
          "url" : "https:\/\/developer.apple.com\/documentation\/RealityKit\/IKComponent\/Joint"
        },
        {
          "description" : "Ordered dictionary like container with fixed size.",
          "name" : "IKComponent.JointCollection",
          "url" : "https:\/\/developer.apple.com\/documentation\/RealityKit\/IKComponent\/JointCollection"
        },
        {
          "description" : "The update stage object that lets you read and update the current settings of a single solver instance.",
          "name" : "IKComponent.Solver",
          "url" : "https:\/\/developer.apple.com\/documentation\/RealityKit\/IKComponent\/Solver"
        },
        {
          "description" : "Ordered dictionary like container with fixed size.",
          "name" : "IKComponent.SolverCollection",
          "url" : "https:\/\/developer.apple.com\/documentation\/RealityKit\/IKComponent\/SolverCollection"
        },
        {
          "description" : "The update stage object that lets you read and update the current settings of a single constraint in an IK solver.",
          "name" : "IKComponent.Constraint",
          "url" : "https:\/\/developer.apple.com\/documentation\/RealityKit\/IKComponent\/Constraint"
        },
        {
          "description" : "Ordered dictionary like container with fixed size.",
          "name" : "IKComponent.ConstraintCollection",
          "url" : "https:\/\/developer.apple.com\/documentation\/RealityKit\/IKComponent\/ConstraintCollection"
        },
        {
          "description" : "A reference counted immutable resource which contains one or more inverse kinematics solver rigs.",
          "name" : "IKResource",
          "url" : "https:\/\/developer.apple.com\/documentation\/RealityKit\/IKResource"
        },
        {
          "description" : "A container describing a solver instance.",
          "name" : "IKSolverDefinition",
          "url" : "https:\/\/developer.apple.com\/documentation\/RealityKit\/IKSolverDefinition"
        }
      ],
      "title" : "Inverse kinematics components"
    },
    {
      "content" : "",
      "items" : [
        {
          "description" : "A full body inverse kinematics rig definition for a single skeleton.",
          "name" : "IKRig",
          "url" : "https:\/\/developer.apple.com\/documentation\/RealityKit\/IKRig"
        },
        {
          "description" : "A definition of a rig joint and its IK solver settings.",
          "name" : "IKRig.Joint",
          "url" : "https:\/\/developer.apple.com\/documentation\/RealityKit\/IKRig\/Joint"
        },
        {
          "description" : "Ordered dictionary-like container with a fixed size.",
          "name" : "IKRig.JointCollection",
          "url" : "https:\/\/developer.apple.com\/documentation\/RealityKit\/IKRig\/JointCollection"
        },
        {
          "description" : "A definition of a rig constraint.",
          "name" : "IKRig.Constraint",
          "url" : "https:\/\/developer.apple.com\/documentation\/RealityKit\/IKRig\/Constraint"
        },
        {
          "description" : "Ordered dictionary-like container.",
          "name" : "IKRig.ConstraintsCollection",
          "url" : "https:\/\/developer.apple.com\/documentation\/RealityKit\/IKRig\/ConstraintsCollection"
        }
      ],
      "title" : "Inverse kinematics rigs"
    },
    {
      "content" : "",
      "items" : [
        {
          "description" : "Explore a collection of projects relating to game development.",
          "name" : "Gaming sample code projects",
          "url" : "https:\/\/developer.apple.com\/documentation\/RealityKit\/game-development-sample-code"
        },
        {
          "description" : "Dynamically move, rotate, and scale entities at runtime.",
          "name" : "Entity animations",
          "url" : "https:\/\/developer.apple.com\/documentation\/RealityKit\/game-development-entity-animations"
        }
      ],
      "title" : "Game development"
    }
  ],
  "source" : "appleJSON",
  "title" : "Character control, skeletons, and inverse kinematics",
  "url" : "https:\/\/developer.apple.com\/documentation\/RealityKit\/game-development-character-skeletons"
}