{
  "abstract" : "Describes the placement and style of the system windowing controls for a scene",
  "codeExamples" : [

  ],
  "conformsTo" : [
    "CVarArg",
    "CustomDebugStringConvertible",
    "CustomStringConvertible",
    "Equatable",
    "Hashable",
    "NSObjectProtocol",
    "Sendable",
    "SendableMetatype"
  ],
  "contentHash" : "f2e8e719ec1c8516ecb0d5640f639b3d511c20e50e593b26e1c48184234a413e",
  "crawledAt" : "2025-12-03T18:47:42Z",
  "declaration" : {
    "code" : "class WindowingControlStyle",
    "language" : "swift"
  },
  "id" : "4144279B-876E-4CC4-A5AF-45535AEA3886",
  "kind" : "class",
  "language" : "swift",
  "module" : "UIKit",
  "platforms" : [
    "iOS",
    "iPadOS",
    "Mac Catalyst",
    "tvOS",
    "visionOS"
  ],
  "rawMarkdown" : "---\nsource: https:\/\/developer.apple.com\/documentation\/UIKit\/UIWindowScene\/WindowingControlStyle\ncrawled: 2025-12-03T18:47:42Z\n---\n\n# UIWindowScene.WindowingControlStyle\n\n**Class**\n\nDescribes the placement and style of the system windowing controls for a scene\n\n## Declaration\n\n```swift\nclass WindowingControlStyle\n```\n\n## Type Properties\n\n- **automatic**: Windowing controls will use the default system style\n- **minimal**: Windowing controls will occupy as little of the scene’s space as possible\n- **unified**: Windowing controls will appear as part of the scene’s content\n\n## Inherits From\n\n- NSObject\n\n## Conforms To\n\n- CVarArg\n- CustomDebugStringConvertible\n- CustomStringConvertible\n- Equatable\n- Hashable\n- NSObjectProtocol\n- Sendable\n- SendableMetatype\n\n",
  "sections" : [
    {
      "content" : "",
      "items" : [
        {
          "description" : "Windowing controls will use the default system style",
          "name" : "automatic",
          "url" : "https:\/\/developer.apple.com\/documentation\/UIKit\/UIWindowScene\/WindowingControlStyle\/automatic"
        },
        {
          "description" : "Windowing controls will occupy as little of the scene’s space as possible",
          "name" : "minimal",
          "url" : "https:\/\/developer.apple.com\/documentation\/UIKit\/UIWindowScene\/WindowingControlStyle\/minimal"
        },
        {
          "description" : "Windowing controls will appear as part of the scene’s content",
          "name" : "unified",
          "url" : "https:\/\/developer.apple.com\/documentation\/UIKit\/UIWindowScene\/WindowingControlStyle\/unified"
        }
      ],
      "title" : "Type Properties"
    },
    {
      "content" : "",
      "items" : [
        {
          "name" : "NSObject"
        }
      ],
      "title" : "Inherits From"
    }
  ],
  "source" : "appleJSON",
  "title" : "UIWindowScene.WindowingControlStyle",
  "url" : "https:\/\/developer.apple.com\/documentation\/UIKit\/UIWindowScene\/WindowingControlStyle"
}