{
  "abstract" : "Sent to the delegate when the user selects a tab bar item.",
  "codeExamples" : [

  ],
  "contentHash" : "99e82f4ed86a6344c4c3cf16b09b65c747151106a094f25f30a1afce67c0e7dd",
  "crawledAt" : "2025-12-05T06:21:13Z",
  "declaration" : {
    "code" : "@MainActor optional func tabBar(_ tabBar: UITabBar, didSelect item: UITabBarItem)",
    "language" : "swift"
  },
  "id" : "4DFB7C5F-B562-4C5B-8212-AAB2CC971C89",
  "kind" : "method",
  "language" : "swift",
  "module" : "UIKit",
  "platforms" : [
    "iOS",
    "iPadOS",
    "Mac Catalyst",
    "tvOS",
    "visionOS"
  ],
  "rawMarkdown" : "---\nsource: https:\/\/developer.apple.com\/documentation\/UIKit\/UITabBarDelegate\/tabBar(_:didSelect:)\ncrawled: 2025-12-05T06:21:13Z\n---\n\n# tabBar(_:didSelect:)\n\n**Instance Method**\n\nSent to the delegate when the user selects a tab bar item.\n\n## Declaration\n\n```swift\n@MainActor optional func tabBar(_ tabBar: UITabBar, didSelect item: UITabBarItem)\n```\n\n## Parameters\n\n- **tabBar**: The tab bar that is being customized.\n- **item**: The tab bar item that was selected.\n\n## Customizing tab bars\n\n- **tabBar(_:willBeginCustomizing:)**: Sent to the delegate before the customizing modal view is displayed.\n- **tabBar(_:didBeginCustomizing:)**: Sent to the delegate after the customizing modal view is displayed.\n- **tabBar(_:willEndCustomizing:changed:)**: Sent to the delegate before the customizing modal view is dismissed.\n- **tabBar(_:didEndCustomizing:changed:)**: Sent to the delegate after the customizing modal view is dismissed.\n\n",
  "sections" : [
    {
      "content" : "",
      "items" : [
        {
          "description" : "Sent to the delegate before the customizing modal view is displayed.",
          "name" : "tabBar(_:willBeginCustomizing:)",
          "url" : "https:\/\/developer.apple.com\/documentation\/UIKit\/UITabBarDelegate\/tabBar(_:willBeginCustomizing:)"
        },
        {
          "description" : "Sent to the delegate after the customizing modal view is displayed.",
          "name" : "tabBar(_:didBeginCustomizing:)",
          "url" : "https:\/\/developer.apple.com\/documentation\/UIKit\/UITabBarDelegate\/tabBar(_:didBeginCustomizing:)"
        },
        {
          "description" : "Sent to the delegate before the customizing modal view is dismissed.",
          "name" : "tabBar(_:willEndCustomizing:changed:)",
          "url" : "https:\/\/developer.apple.com\/documentation\/UIKit\/UITabBarDelegate\/tabBar(_:willEndCustomizing:changed:)"
        },
        {
          "description" : "Sent to the delegate after the customizing modal view is dismissed.",
          "name" : "tabBar(_:didEndCustomizing:changed:)",
          "url" : "https:\/\/developer.apple.com\/documentation\/UIKit\/UITabBarDelegate\/tabBar(_:didEndCustomizing:changed:)"
        }
      ],
      "title" : "Customizing tab bars"
    }
  ],
  "source" : "appleJSON",
  "title" : "tabBar(_:didSelect:)",
  "url" : "https:\/\/developer.apple.com\/documentation\/UIKit\/UITabBarDelegate\/tabBar(_:didSelect:)"
}