{
  "codeExamples" : [

  ],
  "contentHash" : "fec194f0d0968002ef74a5bd6eae26f8dc0b71decf4051fd288ceca0f949aa52",
  "crawledAt" : "2025-12-07T22:52:13Z",
  "id" : "F788D314-00B9-4FE1-8D18-FF65FDB7A718",
  "kind" : "unknown",
  "rawMarkdown" : "---\nsource: https:\/\/developer.apple.com\/documentation\/Spatial\/Vector3D\/Hashable-Implementations\ncrawled: 2025-12-07T22:52:13Z\n---\n\n# Hashable Implementations | Apple Developer Documentation\n\n- [ Spatial ](\/documentation\/spatial)\n\n- [ Vector3D ](\/documentation\/spatial\/vector3d)\n\n- [ Hashable Implementations ](\/documentation\/Spatial\/Vector3D\/Hashable-Implementations)\n\n- [ Vector3D ](\/documentation\/spatial\/vector3d)\n\n-  Hashable Implementations \n\nAPI Collection# Hashable Implementations\n\n## [Topics](\/documentation\/Spatial\/Vector3D\/Hashable-Implementations#topics)\n\n### [Instance Methods](\/documentation\/Spatial\/Vector3D\/Hashable-Implementations#Instance-Methods)\n\n[`func hash(into: inout Hasher)`](\/documentation\/spatial\/vector3d\/hash(into:))Hashes the essential components of this value by feeding them into the given hasher.",
  "sections" : [
    {
      "content" : "",
      "title" : "Topics"
    }
  ],
  "source" : "appleWebKit",
  "title" : "Hashable Implementations | Apple Developer Documentation",
  "url" : "https:\/\/developer.apple.com\/documentation\/Spatial\/Vector3D\/Hashable-Implementations"
}