{
  "abstract" : "Returns true if every element in a vector is exactly equal to the corresponding element in a second vector, and otherwise returns false.",
  "codeExamples" : [

  ],
  "contentHash" : "bc2011a104ec1071d14ae9dce0aa63647b457049c48c55ee4ab65a7e7b458935",
  "crawledAt" : "2025-12-02T02:16:23Z",
  "declaration" : {
    "code" : "func simd_equal(_ x: simd_char16, _ y: simd_char16) -> simd_bool",
    "language" : "swift"
  },
  "id" : "CE02C379-5290-47C8-91B0-73993A4045D7",
  "kind" : "function",
  "module" : "simd",
  "platforms" : [
    "iOS",
    "iPadOS",
    "Mac Catalyst",
    "macOS",
    "tvOS",
    "visionOS",
    "watchOS"
  ],
  "rawMarkdown" : "---\nsource: https:\/\/developer.apple.com\/documentation\/simd\/simd_equal(_:_:)-19z1a\ncrawled: 2025-12-02T02:16:23Z\n---\n\n# simd_equal(_:_:)\n\n**Function**\n\nReturns true if every element in a vector is exactly equal to the corresponding element in a second vector, and otherwise returns false.\n\n## Declaration\n\n```swift\nfunc simd_equal(_ x: simd_char16, _ y: simd_char16) -> simd_bool\n```\n\n## Common Functions\n\n- **simd_abs(_:)**: Returns the absolute value of each element in a vector.\n- **simd_clamp(_:_:_:)**: Returns each element in a vector clamped to a specified range.\n\n",
  "sections" : [
    {
      "content" : "",
      "items" : [
        {
          "description" : "Returns the absolute value of each element in a vector.",
          "name" : "simd_abs(_:)",
          "url" : "https:\/\/developer.apple.com\/documentation\/simd\/simd_abs(_:)-475ng"
        },
        {
          "description" : "Returns each element in a vector clamped to a specified range.",
          "name" : "simd_clamp(_:_:_:)",
          "url" : "https:\/\/developer.apple.com\/documentation\/simd\/simd_clamp(_:_:_:)-509lj"
        }
      ],
      "title" : "Common Functions"
    }
  ],
  "source" : "appleJSON",
  "title" : "simd_equal(_:_:)",
  "url" : "https:\/\/developer.apple.com\/documentation\/simd\/simd_equal(_:_:)-19z1a"
}