{
  "abstract" : "The camera identifier string of the Immersive camera associated with this view model.",
  "codeExamples" : [

  ],
  "contentHash" : "81d11bf00cd94a24f198c777660386be9401c2c5ae5ee877d751150359c930f6",
  "crawledAt" : "2025-12-02T17:16:40Z",
  "declaration" : {
    "code" : "var cameraID: String { get }",
    "language" : "swift"
  },
  "id" : "733458AF-FCCB-4A27-9210-98F08E4A2E30",
  "kind" : "property",
  "language" : "swift",
  "module" : "Immersive Media Support",
  "platforms" : [
    "macOS",
    "visionOS"
  ],
  "rawMarkdown" : "---\nsource: https:\/\/developer.apple.com\/documentation\/ImmersiveMediaSupport\/ImmersiveCameraViewModel\/cameraID\ncrawled: 2025-12-02T17:16:40Z\n---\n\n# cameraID\n\n**Instance Property**\n\nThe camera identifier string of the Immersive camera associated with this view model.\n\n## Declaration\n\n```swift\nvar cameraID: String { get }\n```\n\n## Instance Properties\n\n- **environmentBackdrop**: The environment backdrop associated with the immersive camera view\n- **leftEye**: Left eye mesh associated with the immersive camera view.\n- **mask**: Generated immersive video mask associated with the immersive camera view\n- **rightEye**: Right eye mesh associated with the immersive camera view.\n\n",
  "sections" : [
    {
      "content" : "",
      "items" : [
        {
          "description" : "The environment backdrop associated with the immersive camera view",
          "name" : "environmentBackdrop",
          "url" : "https:\/\/developer.apple.com\/documentation\/ImmersiveMediaSupport\/ImmersiveCameraViewModel\/environmentBackdrop"
        },
        {
          "description" : "Left eye mesh associated with the immersive camera view.",
          "name" : "leftEye",
          "url" : "https:\/\/developer.apple.com\/documentation\/ImmersiveMediaSupport\/ImmersiveCameraViewModel\/leftEye"
        },
        {
          "description" : "Generated immersive video mask associated with the immersive camera view",
          "name" : "mask",
          "url" : "https:\/\/developer.apple.com\/documentation\/ImmersiveMediaSupport\/ImmersiveCameraViewModel\/mask"
        },
        {
          "description" : "Right eye mesh associated with the immersive camera view.",
          "name" : "rightEye",
          "url" : "https:\/\/developer.apple.com\/documentation\/ImmersiveMediaSupport\/ImmersiveCameraViewModel\/rightEye"
        }
      ],
      "title" : "Instance Properties"
    }
  ],
  "source" : "appleJSON",
  "title" : "cameraID",
  "url" : "https:\/\/developer.apple.com\/documentation\/ImmersiveMediaSupport\/ImmersiveCameraViewModel\/cameraID"
}