{
  "codeExamples" : [

  ],
  "contentHash" : "d1c5a25162df3cfc26096b190df64be021b598b072843e6ec795a00ea95dc9f4",
  "crawledAt" : "2025-12-05T18:56:36Z",
  "id" : "646CC4A9-825B-4B6A-B0FC-BCC3FF3DD27F",
  "kind" : "unknown",
  "rawMarkdown" : "---\nsource: https:\/\/developer.apple.com\/documentation\/hypervisor\/hv_vcpu_sme_state_t\/init(streaming_sve_mode_enabled:za_storage_enabled:)\ncrawled: 2025-12-05T18:56:36Z\n---\n\n# init(streaming_sve_mode_enabled:za_storage_enabled:) | Apple Developer Documentation\n\n- [ Hypervisor ](\/documentation\/hypervisor)\n\n- [ hv_vcpu_sme_state_t ](\/documentation\/hypervisor\/hv_vcpu_sme_state_t)\n\n- [ init(streaming_sve_mode_enabled:za_storage_enabled:) ](\/documentation\/hypervisor\/hv_vcpu_sme_state_t\/init(streaming_sve_mode_enabled:za_storage_enabled:))\n\n- [ hv_vcpu_sme_state_t ](\/documentation\/hypervisor\/hv_vcpu_sme_state_t)\n\n-  init(streaming_sve_mode_enabled:za_storage_enabled:) \n\nInitializer# init(streaming_sve_mode_enabled:za_storage_enabled:)\n\nmacOS 15.2+\n\n```\ninit(\n    streaming_sve_mode_enabled: Bool,\n    za_storage_enabled: Bool\n)\n```\n\n## [See Also](\/documentation\/hypervisor\/hv_vcpu_sme_state_t\/init(streaming_sve_mode_enabled:za_storage_enabled:)#see-also)\n\n### [Initializers](\/documentation\/hypervisor\/hv_vcpu_sme_state_t\/init(streaming_sve_mode_enabled:za_storage_enabled:)#Initializers)\n\n[`init()`](\/documentation\/hypervisor\/hv_vcpu_sme_state_t\/init())",
  "sections" : [
    {
      "content" : "",
      "title" : "See Also"
    }
  ],
  "source" : "appleWebKit",
  "title" : "init(streaming_sve_mode_enabled:za_storage_enabled:) | Apple Developer Documentation",
  "url" : "https:\/\/developer.apple.com\/documentation\/hypervisor\/hv_vcpu_sme_state_t\/init(streaming_sve_mode_enabled:za_storage_enabled:)"
}