{
  "abstract" : "A callback to the host for musical context information.",
  "codeExamples" : [

  ],
  "contentHash" : "d66efe1d97f304847ea6c33432b6292ed82ef7dc27a6716afa28598f9fbb0ad3",
  "crawledAt" : "2025-12-02T18:57:50Z",
  "declaration" : {
    "code" : "var musicalContextBlock: AUHostMusicalContextBlock? { get set }",
    "language" : "swift"
  },
  "id" : "041F0588-273B-48E9-9D37-48921F2E3A43",
  "kind" : "property",
  "language" : "swift",
  "module" : "Audio Toolbox",
  "overview" : "## Discussion\n\nAn audio unit accessing this property should cache it in realtime-safe storage before beginning to render.\n\nThis version 3 property is bridged to the version 2 [doc:\/\/com.apple.audiotoolbox\/documentation\/AudioToolbox\/HostCallback_GetBeatAndTempo] and [doc:\/\/com.apple.audiotoolbox\/documentation\/AudioToolbox\/HostCallback_GetMusicalTimeLocation] callback members in the `kAudioUnitProperty_HostCallbacks` API.",
  "platforms" : [
    "iOS",
    "iPadOS",
    "Mac Catalyst",
    "macOS",
    "tvOS",
    "visionOS"
  ],
  "rawMarkdown" : "---\nsource: https:\/\/developer.apple.com\/documentation\/AudioToolbox\/AUAudioUnit\/musicalContextBlock\ncrawled: 2025-12-02T18:57:50Z\n---\n\n# musicalContextBlock\n\n**Instance Property**\n\nA callback to the host for musical context information.\n\n## Declaration\n\n```swift\nvar musicalContextBlock: AUHostMusicalContextBlock? { get set }\n```\n\n## Discussion\n\nAn audio unit accessing this property should cache it in realtime-safe storage before beginning to render.\n\nThis version 3 property is bridged to the version 2 [doc:\/\/com.apple.audiotoolbox\/documentation\/AudioToolbox\/HostCallback_GetBeatAndTempo] and [doc:\/\/com.apple.audiotoolbox\/documentation\/AudioToolbox\/HostCallback_GetMusicalTimeLocation] callback members in the `kAudioUnitProperty_HostCallbacks` API.\n\n## Providing Data to the Host\n\n- **transportStateBlock**: A callback to the host for transport state information.\n- **contextName**: Information about the host context in which the audio unit is connected, for display in the audio unit’s view.\n- **supportsMPE**: A Boolean value that indicates whether the audio unit supports multi-dimensional polyphonic expression.\n- **AUHostMusicalContextBlock**: A block through which hosts provide musical tempo, time signature, and beat position.\n- **AUHostTransportStateBlock**: A block through which hosts provide information about their transport state.\n\n",
  "sections" : [
    {
      "content" : "",
      "items" : [
        {
          "description" : "A callback to the host for transport state information.",
          "name" : "transportStateBlock",
          "url" : "https:\/\/developer.apple.com\/documentation\/AudioToolbox\/AUAudioUnit\/transportStateBlock"
        },
        {
          "description" : "Information about the host context in which the audio unit is connected, for display in the audio unit’s view.",
          "name" : "contextName",
          "url" : "https:\/\/developer.apple.com\/documentation\/AudioToolbox\/AUAudioUnit\/contextName"
        },
        {
          "description" : "A Boolean value that indicates whether the audio unit supports multi-dimensional polyphonic expression.",
          "name" : "supportsMPE",
          "url" : "https:\/\/developer.apple.com\/documentation\/AudioToolbox\/AUAudioUnit\/supportsMPE"
        },
        {
          "description" : "A block through which hosts provide musical tempo, time signature, and beat position.",
          "name" : "AUHostMusicalContextBlock",
          "url" : "https:\/\/developer.apple.com\/documentation\/AudioToolbox\/AUHostMusicalContextBlock"
        },
        {
          "description" : "A block through which hosts provide information about their transport state.",
          "name" : "AUHostTransportStateBlock",
          "url" : "https:\/\/developer.apple.com\/documentation\/AudioToolbox\/AUHostTransportStateBlock"
        }
      ],
      "title" : "Providing Data to the Host"
    }
  ],
  "source" : "appleJSON",
  "title" : "musicalContextBlock",
  "url" : "https:\/\/developer.apple.com\/documentation\/AudioToolbox\/AUAudioUnit\/musicalContextBlock"
}