{
  "codeExamples" : [

  ],
  "contentHash" : "bac2950c4dc9ccf1493bac0989ae4988631e0e73968cf72a9350164a0dba1b55",
  "crawledAt" : "2025-12-07T06:04:05Z",
  "id" : "288AE2EC-9F76-4CA6-B189-996379D53FC7",
  "kind" : "unknown",
  "rawMarkdown" : "---\nsource: https:\/\/developer.apple.com\/documentation\/webkitjs\/htmltablecellelement\/1634287-colspan\ncrawled: 2025-12-07T06:04:05Z\n---\n\n# colSpan | Apple Developer Documentation\n\n- [ WebKit JS ](\/documentation\/webkitjs)\n\n- [ HTMLTableCellElement ](\/documentation\/webkitjs\/htmltablecellelement)\n\n- [ colSpan ](\/documentation\/webkitjs\/htmltablecellelement\/1634287-colspan)\n\n- [ HTMLTableCellElement ](\/documentation\/webkitjs\/htmltablecellelement)\n\n-  colSpan \n\nInstance Property# colSpan\n\nSafari Desktop 10.0+Safari Mobile 10.0+\n\n```\nattribute unsigned long colSpan;\n```\n\n",
  "sections" : [

  ],
  "source" : "appleWebKit",
  "title" : "colSpan | Apple Developer Documentation",
  "url" : "https:\/\/developer.apple.com\/documentation\/webkitjs\/htmltablecellelement\/1634287-colspan"
}