{
  "abstract" : "Creates and returns a `CARenderer` instance with the render target specified by the Core OpenGL context.",
  "codeExamples" : [

  ],
  "contentHash" : "ca588a4147f63ebdf56dd5dba70bc32f00e25bcb4b14a17012146b526ed0d46b",
  "crawledAt" : "2026-03-10T21:35:34Z",
  "declaration" : {
    "code" : "init(cglContext ctx: UnsafeMutableRawPointer, options dict: [AnyHashable : Any]? = nil)",
    "language" : "swift"
  },
  "id" : "195210E2-115D-42BA-BF63-FE75A0E80BD9",
  "kind" : "unknown",
  "language" : "swift",
  "module" : "Core Animation",
  "overview" : "## Return Value\n\nA new instance of `CARenderer` that will use `ctx` as the render target.",
  "platforms" : [
    "Mac Catalyst",
    "macOS"
  ],
  "rawMarkdown" : "---\nsource: https:\/\/developer.apple.com\/documentation\/QuartzCore\/CARenderer\/init(cglContext:options:)\ncrawled: 2026-03-10T21:35:34Z\n---\n\n# init(cglContext:options:)\n\n**Initializer**\n\nCreates and returns a `CARenderer` instance with the render target specified by the Core OpenGL context.\n\n## Declaration\n\n```swift\ninit(cglContext ctx: UnsafeMutableRawPointer, options dict: [AnyHashable : Any]? = nil)\n```\n\n## Parameters\n\n- **ctx**: A Core OpenGL render context that is used as the render target.\n- **dict**: A dictionary of optional parameters.\n\n## Return Value\n\nA new instance of `CARenderer` that will use `ctx` as the render target.\n\n## Creating a Renderer\n\n- **init(mtlTexture:options:)**: Creates a layer renderer from a Metal texture.\n\n",
  "sections" : [
    {
      "content" : "",
      "items" : [
        {
          "description" : "Creates a layer renderer from a Metal texture.",
          "name" : "init(mtlTexture:options:)",
          "url" : "https:\/\/developer.apple.com\/documentation\/QuartzCore\/CARenderer\/init(mtlTexture:options:)"
        }
      ],
      "title" : "Creating a Renderer"
    }
  ],
  "source" : "appleJSON",
  "title" : "init(cglContext:options:)",
  "url" : "https:\/\/developer.apple.com\/documentation\/QuartzCore\/CARenderer\/init(cglContext:options:)"
}