{
  "abstract" : "The stations for the personal recommendation.",
  "codeExamples" : [

  ],
  "contentHash" : "a98b0490b5cf187e7028a38faad24f7505ffc4523b993d3adfea0083f4c97ae3",
  "crawledAt" : "2025-12-04T09:48:34Z",
  "declaration" : {
    "code" : "var stations: MusicItemCollection<Station> { get }",
    "language" : "swift"
  },
  "id" : "16379325-873E-445E-BF43-808884CBA5AE",
  "kind" : "property",
  "language" : "swift",
  "module" : "MusicKit",
  "platforms" : [
    "iOS",
    "iPadOS",
    "Mac Catalyst",
    "macOS",
    "tvOS",
    "visionOS",
    "watchOS"
  ],
  "rawMarkdown" : "---\nsource: https:\/\/developer.apple.com\/documentation\/MusicKit\/MusicPersonalRecommendation\/stations\ncrawled: 2025-12-04T09:48:34Z\n---\n\n# stations\n\n**Instance Property**\n\nThe stations for the personal recommendation.\n\n## Declaration\n\n```swift\nvar stations: MusicItemCollection<Station> { get }\n```\n\n",
  "sections" : [

  ],
  "source" : "appleJSON",
  "title" : "stations",
  "url" : "https:\/\/developer.apple.com\/documentation\/MusicKit\/MusicPersonalRecommendation\/stations"
}