{
  "abstract" : "If `other` does not have a root, append each component of `other`. If `other` has a root, replaces `self` with other.",
  "codeExamples" : [
    {
      "code" : "var path: FilePath = \"\/tmp\"\npath.push(\"dir\/file.txt\") \/\/ path is \"\/tmp\/dir\/file.txt\"\npath.push(\"\/bin\")         \/\/ path is \"\/bin\"",
      "language" : "swift"
    }
  ],
  "contentHash" : "2844102455d91dd8263b06af0c1e3322010784690fc43002ac82f25f277772bb",
  "crawledAt" : "2026-03-10T22:02:30Z",
  "declaration" : {
    "code" : "mutating func push(_ other: FilePath)",
    "language" : "swift"
  },
  "id" : "97FE034D-F595-47D4-BBFC-38A895D67063",
  "kind" : "method",
  "language" : "swift",
  "module" : "System",
  "overview" : "## Discussion\n\nThis operation mimics traversing a directory structure (similar to the `cd` command), where pushing a relative path will append its components and pushing an absolute path will first clear `self`’s existing components.\n\nExample:",
  "platforms" : [
    "iOS",
    "iPadOS",
    "Mac Catalyst",
    "macOS",
    "tvOS",
    "visionOS",
    "watchOS"
  ],
  "rawMarkdown" : "---\nsource: https:\/\/developer.apple.com\/documentation\/System\/FilePath\/push(_:)\ncrawled: 2026-03-10T22:02:30Z\n---\n\n# push(_:)\n\n**Instance Method**\n\nIf `other` does not have a root, append each component of `other`. If `other` has a root, replaces `self` with other.\n\n## Declaration\n\n```swift\nmutating func push(_ other: FilePath)\n```\n\n## Discussion\n\nThis operation mimics traversing a directory structure (similar to the `cd` command), where pushing a relative path will append its components and pushing an absolute path will first clear `self`’s existing components.\n\nExample:\n\n```swift\nvar path: FilePath = \"\/tmp\"\npath.push(\"dir\/file.txt\") \/\/ path is \"\/tmp\/dir\/file.txt\"\npath.push(\"\/bin\")         \/\/ path is \"\/bin\"\n```\n\n",
  "sections" : [

  ],
  "source" : "appleJSON",
  "title" : "push(_:)",
  "url" : "https:\/\/developer.apple.com\/documentation\/System\/FilePath\/push(_:)"
}