{
  "abstract" : "The value that indicates the system allows the Protected Extensible Authentication Protocol (PEAP) for this network.",
  "codeExamples" : [

  ],
  "contentHash" : "9226b5fb83f6ced705e3b6d822e2e74d3b67e8a2240dcd2d1844cc4bd3ddfb46",
  "crawledAt" : "2026-03-10T23:04:14Z",
  "declaration" : {
    "code" : "case peap",
    "language" : "swift"
  },
  "id" : "F6141E03-5D9A-409A-87DD-2E942DCFFE17",
  "kind" : "unknown",
  "language" : "swift",
  "module" : "Wi-Fi Infrastructure",
  "platforms" : [
    "iOS",
    "iPadOS",
    "Mac Catalyst"
  ],
  "rawMarkdown" : "---\nsource: https:\/\/developer.apple.com\/documentation\/WiFiInfrastructure\/WINetworkSharingProvider\/Network\/Credentials-swift.enum\/EAPCredentials\/EAPType\/peap\ncrawled: 2026-03-10T23:04:14Z\n---\n\n# WINetworkSharingProvider.Network.Credentials.EAPCredentials.EAPType.peap\n\n**Case**\n\nThe value that indicates the system allows the Protected Extensible Authentication Protocol (PEAP) for this network.\n\n## Declaration\n\n```swift\ncase peap\n```\n\n",
  "sections" : [

  ],
  "source" : "appleJSON",
  "title" : "WINetworkSharingProvider.Network.Credentials.EAPCredentials.EAPType.peap",
  "url" : "https:\/\/developer.apple.com\/documentation\/WiFiInfrastructure\/WINetworkSharingProvider\/Network\/Credentials-swift.enum\/EAPCredentials\/EAPType\/peap"
}