{
  "codeExamples" : [

  ],
  "contentHash" : "fe6378784d1e085082c07a8938ea00399daf572878163752c1e4adbbdf505228",
  "crawledAt" : "2025-12-12T19:39:21Z",
  "id" : "1A4372E0-467D-4F16-ADAE-52CB3188581B",
  "kind" : "unknown",
  "rawMarkdown" : "---\nsource: https:\/\/developer.apple.com\/documentation\/kernel\/vm_statistics64_data_t\/1573488-pageouts\ncrawled: 2025-12-12T19:39:21Z\n---\n\n# pageouts | Apple Developer Documentation\n\n- [ Kernel ](\/documentation\/kernel)\n\n- [ mach ](\/documentation\/kernel\/mach)\n\n- [ vm ](\/documentation\/kernel\/mach\/vm)\n\n- [ vm_statistics64_data_t ](\/documentation\/kernel\/vm_statistics64_data_t)\n\n- [ pageouts ](\/documentation\/kernel\/vm_statistics64_data_t\/1573488-pageouts)\n\n- [ mach ](\/documentation\/kernel\/mach)\n\n- [ vm ](\/documentation\/kernel\/mach\/vm)\n\n- [ vm_statistics64_data_t ](\/documentation\/kernel\/vm_statistics64_data_t)\n\n-  pageouts \n\nInstance Property# pageouts\n\nmacOS 10.6+\n\n```\nuint64_t pageouts;\n```\n\n",
  "sections" : [

  ],
  "source" : "appleWebKit",
  "title" : "pageouts | Apple Developer Documentation",
  "url" : "https:\/\/developer.apple.com\/documentation\/kernel\/vm_statistics64_data_t\/1573488-pageouts"
}