{
  "abstract" : "STREAM ioctl timeout.",
  "codeExamples" : [

  ],
  "contentHash" : "8a3eebab767e1c273cbe57614fd7cf1cded6f3f3ce3f510177186a50cc6e3adf",
  "crawledAt" : "2025-12-05T08:59:39Z",
  "declaration" : {
    "code" : "static var ETIME: POSIXErrorCode { get }",
    "language" : "swift"
  },
  "id" : "F29286F1-409A-4596-8528-226D444456F4",
  "kind" : "property",
  "language" : "swift",
  "module" : "Foundation",
  "platforms" : [
    "iOS",
    "iPadOS",
    "Mac Catalyst",
    "macOS",
    "tvOS",
    "visionOS",
    "watchOS"
  ],
  "rawMarkdown" : "---\nsource: https:\/\/developer.apple.com\/documentation\/Foundation\/POSIXError\/ETIME\ncrawled: 2025-12-05T08:59:39Z\n---\n\n# ETIME\n\n**Type Property**\n\nSTREAM ioctl timeout.\n\n## Declaration\n\n```swift\nstatic var ETIME: POSIXErrorCode { get }\n```\n\n",
  "sections" : [

  ],
  "source" : "appleJSON",
  "title" : "ETIME",
  "url" : "https:\/\/developer.apple.com\/documentation\/Foundation\/POSIXError\/ETIME"
}