{
  "abstract" : "The condition under which the package manager enables the dependency.",
  "codeExamples" : [

  ],
  "contentHash" : "2da2eb737d10fa88059bc3825eeac799969141b4c1d0857b073150ad24f5fe5a",
  "crawledAt" : "2026-03-10T20:15:17Z",
  "declaration" : {
    "code" : "var condition: Package.Dependency.Trait.Condition?",
    "language" : "swift"
  },
  "id" : "1E517704-587E-4953-A68D-B4BCD183A0E5",
  "kind" : "property",
  "language" : "swift",
  "module" : "PackageDescription",
  "platforms" : [
    "macOS"
  ],
  "rawMarkdown" : "---\nsource: https:\/\/developer.apple.com\/documentation\/PackageDescription\/Package\/Dependency\/Trait\/condition-swift.property\ncrawled: 2026-03-10T20:15:17Z\n---\n\n# condition\n\n**Instance Property**\n\nThe condition under which the package manager enables the dependency.\n\n## Declaration\n\n```swift\nvar condition: Package.Dependency.Trait.Condition?\n```\n\n",
  "sections" : [

  ],
  "source" : "appleJSON",
  "title" : "condition",
  "url" : "https:\/\/developer.apple.com\/documentation\/PackageDescription\/Package\/Dependency\/Trait\/condition-swift.property"
}