{
  "codeExamples" : [

  ],
  "contentHash" : "40e0b921f8272bbb12c09ad7c32856351dc4226fa8fb412bc5b8204dc26e0a92",
  "crawledAt" : "2025-12-05T18:32:09Z",
  "declaration" : {
    "code" : "var x: Float",
    "language" : "swift"
  },
  "id" : "F27403C3-649F-4EAF-AFAB-51F9777A1AF3",
  "kind" : "unknown",
  "rawMarkdown" : "---\nsource: https:\/\/developer.apple.com\/documentation\/metal\/mtlpackedfloatquaternion\/x\ncrawled: 2025-12-05T18:32:09Z\n---\n\n# x | Apple Developer Documentation\n\n- [ Metal ](\/documentation\/metal)\n\n- [ MTLPackedFloatQuaternion ](\/documentation\/metal\/mtlpackedfloatquaternion)\n\n- [ x ](\/documentation\/metal\/mtlpackedfloatquaternion\/x)\n\n- [ MTLPackedFloatQuaternion ](\/documentation\/metal\/mtlpackedfloatquaternion)\n\n-  x \n\nInstance Property# x\n\niOSiPadOSMac CatalystmacOStvOSvisionOS\n\n```\nvar x: Float\n```\n\n",
  "sections" : [

  ],
  "source" : "appleWebKit",
  "title" : "x | Apple Developer Documentation",
  "url" : "https:\/\/developer.apple.com\/documentation\/metal\/mtlpackedfloatquaternion\/x"
}