{
  "codeExamples" : [

  ],
  "contentHash" : "63df79fe1a935c2c70c1c8bc7a24a6d7780d25564cffa47e50f4159d3fd34537",
  "crawledAt" : "2025-12-09T22:28:54Z",
  "declaration" : {
    "code" : "func min() -> Just<Output>",
    "language" : "swift"
  },
  "id" : "AF94BA92-F0CC-4F59-9693-4D91F0974AA1",
  "kind" : "unknown",
  "rawMarkdown" : "---\nsource: https:\/\/developer.apple.com\/documentation\/Combine\/Just\/min()\ncrawled: 2025-12-09T22:28:54Z\n---\n\n# min() | Apple Developer Documentation\n\n- [ Combine ](\/documentation\/combine)\n\n- [ Just ](\/documentation\/combine\/just)\n\n- [ min() ](\/documentation\/Combine\/Just\/min())\n\n- [ Just ](\/documentation\/combine\/just)\n\n-  min() \n\nInstance Method# min()\n\niOS 13.0+iPadOS 13.0+Mac Catalyst 13.0+macOS 10.15+tvOS 13.0+visionOS 1.0+watchOS 6.0+\n\n```\nfunc min() -> Just<Output>\n```\n\nAvailable when `Output` conforms to `Comparable`.## [See Also](\/documentation\/Combine\/Just\/min()#see-also)\n\n### [Applying mathematical operations on elements](\/documentation\/Combine\/Just\/min()#Applying-mathematical-operations-on-elements)\n\n[`func count() -> Just<Int>`](\/documentation\/combine\/just\/count())[`func max() -> Just<Output>`](\/documentation\/combine\/just\/max())[`func max(by: (Output, Output) -> Bool) -> Just<Output>`](\/documentation\/combine\/just\/max(by:))[`func min(by: (Output, Output) -> Bool) -> Just<Output>`](\/documentation\/combine\/just\/min(by:))",
  "sections" : [
    {
      "content" : "",
      "title" : "See Also"
    }
  ],
  "source" : "appleWebKit",
  "title" : "min() | Apple Developer Documentation",
  "url" : "https:\/\/developer.apple.com\/documentation\/Combine\/Just\/min()"
}