{
  "abstract" : "The anchor for the plane that the ray intersected.",
  "codeExamples" : [

  ],
  "contentHash" : "4cee2f771416dec0849a99ad20fe37f01fb3fef02ec182a4840819d4ff32ed1f",
  "crawledAt" : "2025-12-02T18:34:42Z",
  "declaration" : {
    "code" : "var anchor: ARAnchor? { get }",
    "language" : "swift"
  },
  "id" : "D56AD1C7-A10D-4F9B-B5CA-C1ABC3C73FBD",
  "kind" : "property",
  "language" : "swift",
  "module" : "ARKit",
  "overview" : "## Discussion\n\nIf you chose an existing plane target, ARKit provides its anchor. If you choose an estimated plane target, ARKit provides an anchor only if the ray intersects an existing plane.",
  "platforms" : [
    "iOS",
    "iPadOS",
    "Mac Catalyst"
  ],
  "rawMarkdown" : "---\nsource: https:\/\/developer.apple.com\/documentation\/ARKit\/ARRaycastResult\/anchor\ncrawled: 2025-12-02T18:34:42Z\n---\n\n# anchor\n\n**Instance Property**\n\nThe anchor for the plane that the ray intersected.\n\n## Declaration\n\n```swift\nvar anchor: ARAnchor? { get }\n```\n\n## Discussion\n\nIf you chose an existing plane target, ARKit provides its anchor. If you choose an estimated plane target, ARKit provides an anchor only if the ray intersects an existing plane.\n\n## Identifying Results\n\n- **worldTransform**: The position, rotation, and scale, of the ray’s intersection with the target.\n- **target**: The type of surface that the ray intersects.\n- **ARRaycastQuery.Target**: The types of surface you allow a raycast to intersect with.\n- **targetAlignment**: The alignment of the plane that the ray intersected.\n- **ARRaycastQuery.TargetAlignment**: A specification that indicates a target’s alignment with respect to gravity\n\n",
  "sections" : [
    {
      "content" : "",
      "items" : [
        {
          "description" : "The position, rotation, and scale, of the ray’s intersection with the target.",
          "name" : "worldTransform",
          "url" : "https:\/\/developer.apple.com\/documentation\/ARKit\/ARRaycastResult\/worldTransform"
        },
        {
          "description" : "The type of surface that the ray intersects.",
          "name" : "target",
          "url" : "https:\/\/developer.apple.com\/documentation\/ARKit\/ARRaycastResult\/target"
        },
        {
          "description" : "The types of surface you allow a raycast to intersect with.",
          "name" : "ARRaycastQuery.Target",
          "url" : "https:\/\/developer.apple.com\/documentation\/ARKit\/ARRaycastQuery\/Target-swift.enum"
        },
        {
          "description" : "The alignment of the plane that the ray intersected.",
          "name" : "targetAlignment",
          "url" : "https:\/\/developer.apple.com\/documentation\/ARKit\/ARRaycastResult\/targetAlignment"
        },
        {
          "description" : "A specification that indicates a target’s alignment with respect to gravity",
          "name" : "ARRaycastQuery.TargetAlignment",
          "url" : "https:\/\/developer.apple.com\/documentation\/ARKit\/ARRaycastQuery\/TargetAlignment-swift.enum"
        }
      ],
      "title" : "Identifying Results"
    }
  ],
  "source" : "appleJSON",
  "title" : "anchor",
  "url" : "https:\/\/developer.apple.com\/documentation\/ARKit\/ARRaycastResult\/anchor"
}