{
  "abstract" : "Device’s Wi-Fi Aware’s service name.",
  "codeExamples" : [

  ],
  "contentHash" : "dffb28dc2e206c2a123e34097327204c25f67b15285071a858cb255adbe497a9",
  "crawledAt" : "2025-12-02T12:08:27Z",
  "declaration" : {
    "code" : "var wifiAwareServiceName: String? { get set }",
    "language" : "swift"
  },
  "id" : "3FC4A371-9913-4B4D-9D21-501D9B90B631",
  "kind" : "property",
  "module" : "DeviceDiscoveryExtension",
  "platforms" : [
    "iOS",
    "iPadOS",
    "Mac Catalyst",
    "macOS",
    "visionOS"
  ],
  "rawMarkdown" : "---\nsource: https:\/\/developer.apple.com\/documentation\/DeviceDiscoveryExtension\/DDDevice\/wifiAwareServiceName\ncrawled: 2025-12-02T12:08:27Z\n---\n\n# wifiAwareServiceName\n\n**Instance Property**\n\nDevice’s Wi-Fi Aware’s service name.\n\n## Declaration\n\n```swift\nvar wifiAwareServiceName: String? { get set }\n```\n\n",
  "sections" : [

  ],
  "source" : "appleJSON",
  "title" : "wifiAwareServiceName",
  "url" : "https:\/\/developer.apple.com\/documentation\/DeviceDiscoveryExtension\/DDDevice\/wifiAwareServiceName"
}